LICENSE
MANIFEST.in
TODO
fedora-devshell.spec
setup.py
devshell/__init__.py
devshell/devshell.py
devshell/diff.excludes
devshell/ports.py
devshell/base/__init__.py
devshell/base/awk.py
devshell/base/base.py
devshell/base/exceptions.py
devshell/base/factories.py
devshell/base/module.py
devshell/base/profiles.py
devshell/base/rpm_utils.py
devshell/base/util.py
devshell/base/validators.py
devshell/base/vars.py
devshell/modules/__init__.py
devshell/modules/audit.py
devshell/modules/autotools.py
devshell/modules/bugs.py
devshell/modules/build.py
devshell/modules/buildsystem.py
devshell/modules/cabal.py
devshell/modules/darcs.py
devshell/modules/directory.py
devshell/modules/fedorahostedgitfetcher.py
devshell/modules/fedorahostedgitport.py
devshell/modules/fetcher.py
devshell/modules/freejport.py
devshell/modules/git.py
devshell/modules/hackage.py
devshell/modules/haskellport.py
devshell/modules/mail.py
devshell/modules/mock.py
devshell/modules/package.py
devshell/modules/packagesource.py
devshell/modules/port.py
devshell/modules/profile.py
devshell/modules/revisioncontrol.py
devshell/modules/revisorport.py
devshell/modules/rpmcvspackage.py
devshell/modules/source.py
devshell/modules/sourceball.py
fedora_devshell.egg-info/PKG-INFO
fedora_devshell.egg-info/SOURCES.txt
fedora_devshell.egg-info/dependency_links.txt
fedora_devshell.egg-info/entry_points.txt
fedora_devshell.egg-info/requires.txt
fedora_devshell.egg-info/top_level.txt