Metadata-Version: 1.0
Name: fedora-devshell
Version: 0.1.1
Summary: Fedora Developer's Lunchbox
Home-page: https://fedoraproject.org/wiki/Devshell
Author: Yaakov M. Nemoy
Author-email: devshell@hexago.nl
License: GPLv2+
Platform: UNKNOWN
Classifier: Development Status :: 3 - Alpha
Classifier: Environment :: Console
Classifier: Intended Audience :: Developers
Classifier: Intended Audience :: Information Technology
Classifier: Intended Audience :: System Administrators
Classifier: License :: OSI Approved :: GNU General Public License (GPL)
Classifier: Operating System :: POSIX :: Linux
Classifier: Topic :: Software Development :: Build Tools
Classifier: Topic :: System :: Shells
